[
  {
    "id": "822665917225",
    "sellerId": "PsV0VneTFkJfB+HuEqW4fg==",
    "name": "Brand new special price maurizio amadei m.a+ MA+ purchased from European counters with discounts. There are traces of trying on. Mind if you mind, please don&#39;t take pictures. It smells good if you use it yourself. The price is also very good. Size: 41 leather shoes are 1 size larger. Usually 41.5-42.5 can be worn. The second generation of MA brand is obviously better and more casual than other pioneer brands. Very beautiful white sneaker shoes...",
    "price": 495,
    "created": 1722992796,
    "thumbnails": [
      "http://img.alicdn.com/bao/uploaded/i2/O1CN01LhYPvH1qRqZEP0ZjR_!!0-fleamarket.jpg"
    ],
    "categoryId": "50012906",
    "href": "https://2.taobao.com/item-detail?itemId=822665917225&spm=a2170.xianyu_tbpc_search.0.0",
    "website": "xianyu",
    "location": "china"
  },
  {
    "id": "846351780246",
    "sellerId": "xpbmD/2MlrOcQ6TmUWp9kw==",
    "name": "M.a+ by Maurizio Amadei is a top handmade brand from Italy, combining experimental and artistic elements. Narrow Oxford shoes, leather, beige, No. 41, authentic brand new, free shipping, customs clearance, 2-3 weeks for forwarding, free shipping by DHL, 7 working days",
    "price": 502,
    "created": 1729556551,
    "thumbnails": [
      "http://img.alicdn.com/bao/uploaded/i3/O1CN01GCAho71xggji1ilSi_!!0-fleamarket.jpg"
    ],
    "categoryId": "50012906",
    "href": "https://2.taobao.com/item-detail?itemId=846351780246&spm=a2170.xianyu_tbpc_search.0.0",
    "website": "xianyu",
    "location": "china"
  },
  {
    "id": "704121436710",
    "sellerId": "D9rIhQ6BLN2H2oh9QB4+ZQ==",
    "name": "m.a+ Black dress size 40, bust 37, length 100 Direct mail from Japan, shipped within a week",
    "price": 198,
    "created": 1677287087,
    "thumbnails": [
      "http://img.alicdn.com/bao/uploaded/i4/O1CN01WSiIYQ2J7LXHrGPLT_!!53-fleamarket.heic"
    ],
    "categoryId": "50010850",
    "href": "https://2.taobao.com/item-detail?itemId=704121436710&spm=a2170.xianyu_tbpc_search.0.0",
    "website": "xianyu",
    "location": "china"
  },
  {
    "id": "755187985388",
    "sellerId": "JskbGD/L9R6ioEacBHO4tQ==",
    "name": "m.a+ second-hand boots 41 suede is very soft. Bought in Taikoo Li Sanlitun. Worn less than 5 times. The sole is not worn. Patched. #wear new shoes for changing seasons#daily life of shoe control#must-have trendy shoes for street",
    "price": 523,
    "created": 1702371373,
    "thumbnails": [
      "http://img.alicdn.com/bao/uploaded/i2/O1CN01DBQZIJ1DscdVfpQbM_!!53-fleamarket.heic"
    ],
    "categoryId": "50011743",
    "href": "https://2.taobao.com/item-detail?itemId=755187985388&spm=a2170.xianyu_tbpc_search.0.0",
    "website": "xianyu",
    "location": "china"
  },
  {
    "id": "853833651886",
    "sellerId": "MwwfjAP6MCtaHoZIRDEOcg==",
    "name": "M.A+ by Maurizio Amadei classic black underarm bag grained cowhide + 925 silver brand new spot real shot including bags for those who know the goods #DarkCoolGirl",
    "price": 583,
    "created": 1731769581,
    "thumbnails": [
      "http://img.alicdn.com/bao/uploaded/i1/O1CN013wlFlY1MF55Sas2cn_!!4611686018427385484-0-fleamarket.jpg"
    ],
    "categoryId": "50012010",
    "href": "https://2.taobao.com/item-detail?itemId=853833651886&spm=a2170.xianyu_tbpc_search.0.0",
    "website": "xianyu",
    "location": "china"
  },
  {
    "id": "637379896537",
    "sellerId": "eGMSLLpsIfTDjfqRxrWrSw==",
    "name": "M.A+ by Maurizio Amadei Pyramid Handbag Small Black cowhide Seamless structure Hand-folded Signature &quot;+&quot; Vintage silver details Small size is approximately 23*19 Handbag not included",
    "price": 490,
    "created": 1612419513,
    "thumbnails": [
      "http://img.alicdn.com/bao/uploaded/i4/O1CN01uqbGc21UfCJMhmY5f_!!0-fleamarket.jpg"
    ],
    "categoryId": "50012010",
    "href": "https://2.taobao.com/item-detail?itemId=637379896537&spm=a2170.xianyu_tbpc_search.0.0",
    "website": "xianyu",
    "location": "china"
  },
  {
    "id": "781670945364",
    "sellerId": "XeqCF4wVNngxCAQaGyw88g==",
    "name": "M.A+ BY MAURIZIO AMADEI MA+ classic shell foreskin rope model red genuine product with purchase record 8 new lining with black dyeing, no refund or exchange by default",
    "price": 198,
    "created": 1712559187,
    "thumbnails": [
      "http://img.alicdn.com/bao/uploaded/i3/O1CN01fkIA371DJoZg4Z0nt_!!0-fleamarket.jpg"
    ],
    "categoryId": "50012010",
    "href": "https://2.taobao.com/item-detail?itemId=781670945364&spm=a2170.xianyu_tbpc_search.0.0",
    "website": "xianyu",
    "location": "china"
  },
  {
    "id": "842481621276",
    "sellerId": "/ZQbFyNpuoBT7ApHxfZXxg==",
    "name": "m.a+ silver chain shell bag, I have carried it two or three times without any flaws. The ink bag I bought does not have a dust bag. Only the bag is available, please do not bother me if you want to bargain.",
    "price": 341,
    "created": 1728542082,
    "thumbnails": [
      "http://img.alicdn.com/bao/uploaded/i4/O1CN011Uuqvq1w1dcIW3BXP_!!0-fleamarket.jpg"
    ],
    "categoryId": "50012010",
    "href": "https://2.taobao.com/item-detail?itemId=842481621276&spm=a2170.xianyu_tbpc_search.0.0",
    "website": "xianyu",
    "location": "china"
  },
  {
    "id": "711872508447",
    "sellerId": "sBriJUztGD4QbEmyMII3kg==",
    "name": "[Brand new, shipped in seconds] M.A+ Maurizio Amadei 23 autumn and winter new double ring shell bag red line cross purchase guarantee authenticity, don&#39;t come if you don&#39;t believe it. I like new things and I&#39;ve never worn a brand new one! Except for the first three pictures, the other pictures are real shots! The new model is camel leather, which is different from the leather of the previous shell bag. If you can accept the price, ask again. We don&#39;t sell at a low price. If you understand the brand&#39;s handmade traces, come to borrow CDG, Yohji Ya...",
    "price": 487,
    "created": 1681150510,
    "thumbnails": [
      "http://img.alicdn.com/bao/uploaded/i3/O1CN01pm39qR2MSMdHJtrq9_!!53-fleamarket.heic"
    ],
    "categoryId": "50012010",
    "href": "https://2.taobao.com/item-detail?itemId=711872508447&spm=a2170.xianyu_tbpc_search.0.0",
    "website": "xianyu",
    "location": "china"
  },
  {
    "id": "666845346823",
    "sellerId": "LdLexICRkFC4kj/m08+J4w==",
    "name": "M.a+ Shell Bag",
    "price": 391,
    "created": 1641685096,
    "thumbnails": [
      "http://img.alicdn.com/bao/uploaded/i1/O1CN01eMFmbQ21Yg0UEep6r_!!0-fleamarket.jpg"
    ],
    "categoryId": "50012010",
    "href": "https://2.taobao.com/item-detail?itemId=666845346823&spm=a2170.xianyu_tbpc_search.0.0",
    "website": "xianyu",
    "location": "china"
  },
  {
    "id": "726321698377",
    "sellerId": "SKbu5+Yo6joaChYXv9zc5Q==",
    "name": "m.a+ by Maurizio amadei 24ss 2 4 Spring and Summer accepts reservations. The deposit is settled at the real-time exchange rate of the Euro. No refund if the order is cancelled. Complete formal customs clearance procedures. No loss if you place an order. Default SF Express payment, no refund or exchange after sale.",
    "price": 318,
    "created": 1687787286,
    "thumbnails": [
      "http://img.alicdn.com/bao/uploaded/i2/O1CN01YGRt1T21rul6yZKWR_!!53-fleamarket.heic"
    ],
    "categoryId": "50012010",
    "href": "https://2.taobao.com/item-detail?itemId=726321698377&spm=a2170.xianyu_tbpc_search.0.0",
    "website": "xianyu",
    "location": "china"
  },
  {
    "id": "811779417305",
    "sellerId": "PsV0VneTFkJfB+HuEqW4fg==",
    "name": "Brand new with suspenders ➕ m.a+ by Maurizio Amadei ➕ black side hand-stitched slim-fit trousers graduated model Made in Italy Size: 46 Waist 41, Length 102, Thigh 29, Back Waist to Crotch 31 In stock and shipped in seconds Bought from offline buyer store Original price more than 10,000 Good price to sell idle",
    "price": 858,
    "created": 1720054906,
    "thumbnails": [
      "http://img.alicdn.com/bao/uploaded/i2/O1CN01jsiybr1qRqYeA8H1f_!!0-fleamarket.jpg"
    ],
    "categoryId": "3035",
    "href": "https://2.taobao.com/item-detail?itemId=811779417305&spm=a2170.xianyu_tbpc_search.0.0",
    "website": "xianyu",
    "location": "china"
  },
  {
    "id": "846154241109",
    "sellerId": "xpbmD/2MlrOcQ6TmUWp9kw==",
    "name": "M.a+ by Maurizio Amadei is a top handmade brand from Italy, combining experimental and artistic elements. High boots with zipper, thick sole and low heel, leather, red, authentic and brand new from No. 39 overseas buyer store, free shipping, customs clearance in 2-3 weeks, free shipping by DHL in 7 working days",
    "price": 529,
    "created": 1729556978,
    "thumbnails": [
      "http://img.alicdn.com/bao/uploaded/i4/O1CN01Qe3VsD1xggjhU87PC_!!0-fleamarket.jpg"
    ],
    "categoryId": "50011743",
    "href": "https://2.taobao.com/item-detail?itemId=846154241109&spm=a2170.xianyu_tbpc_search.0.0",
    "website": "xianyu",
    "location": "china"
  },
  {
    "id": "759988145320",
    "sellerId": "+cHR4UqVkmz2QFswDyupuA==",
    "name": "m.a+ Maurizio Amadei Black horse leather long chicken nugget bag Brand new No returns or exchanges once sold Only SF Express cash on delivery is accepted",
    "price": 899,
    "created": 1704187808,
    "thumbnails": [
      "http://img.alicdn.com/bao/uploaded/i2/O1CN01XVGJYO1DYTDR3Qdyz_!!0-fleamarket.jpg"
    ],
    "categoryId": "50012010",
    "href": "https://2.taobao.com/item-detail?itemId=759988145320&spm=a2170.xianyu_tbpc_search.0.0",
    "website": "xianyu",
    "location": "china"
  },
  {
    "id": "842688483290",
    "sellerId": "xpbmD/2MlrOcQ6TmUWp9kw==",
    "name": "M.a+ by Maurizio Amadei is a top handmade brand from Italy, combining experimental and artistic elements. Low-grade pocket pants in black, authentic brand new from No. 44 overseas buyer store, free shipping, customs clearance in 2-3 weeks, free shipping by DHL in 7 working days",
    "price": 346,
    "created": 1728685175,
    "thumbnails": [
      "http://img.alicdn.com/bao/uploaded/i4/O1CN01LaKPLd1xggjRvaCNR_!!0-fleamarket.jpg"
    ],
    "categoryId": "3035",
    "href": "https://2.taobao.com/item-detail?itemId=842688483290&spm=a2170.xianyu_tbpc_search.0.0",
    "website": "xianyu",
    "location": "china"
  }
]