[
  {
    "id": "728879829911",
    "sellerId": "n+Dhz3idk3nx96t2pmWf2A==",
    "name": "国内现货 SALE！M.A+ Maurizio Amadei 大号贝壳包 暗红色 硬皮 实拍 可手提 单肩 自留款  同款红色上身图参考 清货折扣  原价过万",
    "price": 538,
    "created": 1689272625,
    "thumbnails": [
      "http://img.alicdn.com/bao/uploaded/i4/O1CN01qB90EU1z4n3FIClpu_!!53-fleamarket.heic"
    ],
    "categoryId": "50012010",
    "href": "https://2.taobao.com/item-detail?itemId=728879829911&spm=a2170.xianyu_tbpc_search.0.0",
    "website": "xianyu",
    "location": "china"
  },
  {
    "id": "810343926611",
    "sellerId": "3mvkQrybutr9rJ8QVSEMKg==",
    "name": "maurizio amadei m.a+ 需要了解更多款式及价格请私信～  ➕",
    "price": 86,
    "created": 1719622720,
    "thumbnails": [
      "http://img.alicdn.com/bao/uploaded/i3/O1CN01bfX1Tn2BMuDSD1IrA_!!0-fleamarket.jpg"
    ],
    "categoryId": "50012028",
    "href": "https://2.taobao.com/item-detail?itemId=810343926611&spm=a2170.xianyu_tbpc_search.0.0",
    "website": "xianyu",
    "location": "china"
  },
  {
    "id": "781670945364",
    "sellerId": "XeqCF4wVNngxCAQaGyw88g==",
    "name": "M.A+ BY MAURIZIO AMADEI MA+ 经典 贝壳包 皮绳款 红色 正品 有购买记录 8新 内里有染黑   拍下默认不退换",
    "price": 198,
    "created": 1712559187,
    "thumbnails": [
      "http://img.alicdn.com/bao/uploaded/i3/O1CN01fkIA371DJoZg4Z0nt_!!0-fleamarket.jpg"
    ],
    "categoryId": "50012010",
    "href": "https://2.taobao.com/item-detail?itemId=781670945364&spm=a2170.xianyu_tbpc_search.0.0",
    "website": "xianyu",
    "location": "china"
  },
  {
    "id": "764211201232",
    "sellerId": "7BRXoXMDmbrj3J9N5P+dLQ==",
    "name": "M.A+ 链条包 砍价勿扰，售出不退不换",
    "price": 737,
    "created": 1705821808,
    "thumbnails": [
      "http://img.alicdn.com/bao/uploaded/i3/O1CN01j65QnQ2N9sI1F4tVV_!!0-fleamarket.jpg"
    ],
    "categoryId": "50012010",
    "href": "https://2.taobao.com/item-detail?itemId=764211201232&spm=a2170.xianyu_tbpc_search.0.0",
    "website": "xianyu",
    "location": "china"
  },
  {
    "id": "785497029609",
    "sellerId": "F4E1R/vapYsyoYHsop1O8A==",
    "name": "M.A+  23AW 链条夹子包 现货 全新  国现",
    "price": 880,
    "created": 1713419740,
    "thumbnails": [
      "http://img.alicdn.com/bao/uploaded/i1/O1CN01GxQ01x2Kgu261ZvV3_!!53-fleamarket.heic"
    ],
    "categoryId": "50012010",
    "href": "https://2.taobao.com/item-detail?itemId=785497029609&spm=a2170.xianyu_tbpc_search.0.0",
    "website": "xianyu",
    "location": "china"
  },
  {
    "id": "765104873669",
    "sellerId": "pkvnOU/0j/0PvJmjVscMGQ==",
    "name": "m.a+ by Maurizio Amadei 黑色不规则斜跨包  全新正品 发货前拍照确认 售出（拍下，快递发出）不支持退换 顺丰包邮",
    "price": 504,
    "created": 1706201901,
    "thumbnails": [
      "http://img.alicdn.com/bao/uploaded/i2/O1CN01xZZZni1pXyBuU6thP_!!0-fleamarket.jpg"
    ],
    "categoryId": "50012010",
    "href": "https://2.taobao.com/item-detail?itemId=765104873669&spm=a2170.xianyu_tbpc_search.0.0",
    "website": "xianyu",
    "location": "china"
  },
  {
    "id": "656734269869",
    "sellerId": "bVcXT2vt9RLlhezZxciW7w==",
    "name": "M.a+ maurizio amedei贝壳包 纯银链条 白色 全新 包装在 正品 随意鉴定 不议价 不退换 下图为实拍",
    "price": 440,
    "created": 1633425070,
    "thumbnails": [
      "http://img.alicdn.com/bao/uploaded/i1/O1CN01C9grHa2GIODn2Dzce_!!0-fleamarket.jpg"
    ],
    "categoryId": "50012010",
    "href": "https://2.taobao.com/item-detail?itemId=656734269869&spm=a2170.xianyu_tbpc_search.0.0",
    "website": "xianyu",
    "location": "china"
  },
  {
    "id": "728670964637",
    "sellerId": "n+Dhz3idk3nx96t2pmWf2A==",
    "name": "国内现货 SALE！  M.A+ Maurizio Amad ei  大号贝壳包  黑色（改色）软皮 防尘袋搬店的时候丢失了  实拍  折上折亏出 上身图参考",
    "price": 438,
    "created": 1689273211,
    "thumbnails": [
      "http://img.alicdn.com/bao/uploaded/i2/O1CN01gCIFtD1z4n3PRmcwR_!!53-fleamarket.heic"
    ],
    "categoryId": "50012010",
    "href": "https://2.taobao.com/item-detail?itemId=728670964637&spm=a2170.xianyu_tbpc_search.0.0",
    "website": "xianyu",
    "location": "china"
  },
  {
    "id": "764228118851",
    "sellerId": "7BRXoXMDmbrj3J9N5P+dLQ==",
    "name": "M.A+ 短靴，全新现货37，38码 砍价勿扰，售出不退不换",
    "price": 924,
    "created": 1705820863,
    "thumbnails": [
      "http://img.alicdn.com/bao/uploaded/i4/O1CN01TmGxv02N9sI1E9DxD_!!0-fleamarket.jpg"
    ],
    "categoryId": "50012028",
    "href": "https://2.taobao.com/item-detail?itemId=764228118851&spm=a2170.xianyu_tbpc_search.0.0",
    "website": "xianyu",
    "location": "china"
  },
  {
    "id": "633083842097",
    "sellerId": "n+Dhz3idk3nx96t2pmWf2A==",
    "name": "国内现货 特价 m.a+  马皮高跟靴 原价1w+ 36码 当天顺丰发出 鞋盒 防尘袋 齐全",
    "price": 425,
    "created": 1606736761,
    "thumbnails": [
      "http://img.alicdn.com/bao/uploaded/i4/O1CN01cbhgH41K9v1co3M9L_!!0-fleamarket.jpg"
    ],
    "categoryId": "50012028",
    "href": "https://2.taobao.com/item-detail?itemId=633083842097&spm=a2170.xianyu_tbpc_search.0.0",
    "website": "xianyu",
    "location": "china"
  }
]